{
  "diagnosis": {
    "best_model": "improved_relu_256_128_momentum",
    "resolved_model": "resolved_relu_256_128_l2_earlystop",
    "accuracy_gain_vs_previous_pp": 0.27000000000000357,
    "accuracy_delta_resolved_vs_problem_pp": -0.30000000000000027,
    "improved_gap_pp": 2.0299999999999985,
    "resolved_gap_pp": 1.200000000000001,
    "gap_reduction_pp": 0.8299999999999974,
    "improved_val_drop_pp": 0.039999999999995595,
    "resolved_val_drop_pp": 0.0,
    "improved_val_data_loss_rise": 0.003618977963924408,
    "resolved_val_data_loss_rise": 0.0,
    "conclusion": "O problema encontrado foi overfitting leve no modelo improved: treino quase perfeito e gap treino-validacao de 2.03 p.p. A resolucao aplicada foi early stopping por val_data_loss com restauracao do melhor checkpoint. O gap caiu para 1.20 p.p. e a acuracia de teste ficou em 97.86%."
  },
  "models": [
    {
      "name": "compact_relu_64_32",
      "test_accuracy": 0.9634,
      "test_data_loss": 0.1245667114853859,
      "test_objective_loss": 0.1245667114853859,
      "final_train_accuracy": 0.9691,
      "final_val_accuracy": 0.9625,
      "final_train_data_loss": 0.10735976696014404,
      "final_val_data_loss": 0.13801303505897522,
      "final_generalization_gap_pp": 0.6599999999999939,
      "best_val_accuracy": 0.9625,
      "best_val_accuracy_epoch": 8,
      "final_val_accuracy_drop_from_best_pp": 0.0,
      "best_val_data_loss": 0.13801303505897522,
      "best_val_data_loss_epoch": 8,
      "final_val_data_loss_rise_from_best": 0.0,
      "selected_epoch": 8,
      "epochs_run": 8,
      "early_stopping": false,
      "stopped_epoch": null,
      "diagnosis": "sem sinal material"
    },
    {
      "name": "final_relu_128_64",
      "test_accuracy": 0.9759,
      "test_data_loss": 0.08210042119026184,
      "test_objective_loss": 0.08210042119026184,
      "final_train_accuracy": 0.9858,
      "final_val_accuracy": 0.9709,
      "final_train_data_loss": 0.05098526552319527,
      "final_val_data_loss": 0.0984858050942421,
      "final_generalization_gap_pp": 1.4900000000000024,
      "best_val_accuracy": 0.9709,
      "best_val_accuracy_epoch": 10,
      "final_val_accuracy_drop_from_best_pp": 0.0,
      "best_val_data_loss": 0.0984858050942421,
      "best_val_data_loss_epoch": 10,
      "final_val_data_loss_rise_from_best": 0.0,
      "selected_epoch": 10,
      "epochs_run": 10,
      "early_stopping": false,
      "stopped_epoch": null,
      "diagnosis": "sem sinal material"
    },
    {
      "name": "improved_relu_256_128_momentum",
      "test_accuracy": 0.9816,
      "test_data_loss": 0.06072347238659859,
      "test_objective_loss": 0.1012982502579689,
      "final_train_accuracy": 1.0,
      "final_val_accuracy": 0.9797,
      "final_train_data_loss": 0.002960697514936328,
      "final_val_data_loss": 0.07709967344999313,
      "final_generalization_gap_pp": 2.0299999999999985,
      "best_val_accuracy": 0.9801,
      "best_val_accuracy_epoch": 13,
      "final_val_accuracy_drop_from_best_pp": 0.039999999999995595,
      "best_val_data_loss": 0.07348069548606873,
      "best_val_data_loss_epoch": 8,
      "final_val_data_loss_rise_from_best": 0.003618977963924408,
      "selected_epoch": 15,
      "epochs_run": 15,
      "early_stopping": false,
      "stopped_epoch": null,
      "diagnosis": "overfitting leve"
    },
    {
      "name": "resolved_relu_256_128_l2_earlystop",
      "test_accuracy": 0.9786,
      "test_data_loss": 0.06937826424837112,
      "test_objective_loss": 0.18066605925559998,
      "final_train_accuracy": 0.9906,
      "final_val_accuracy": 0.9786,
      "final_train_data_loss": 0.040536221116781235,
      "final_val_data_loss": 0.07600118964910507,
      "final_generalization_gap_pp": 1.200000000000001,
      "best_val_accuracy": 0.9786,
      "best_val_accuracy_epoch": 8,
      "final_val_accuracy_drop_from_best_pp": 0.0,
      "best_val_data_loss": 0.07600118964910507,
      "best_val_data_loss_epoch": 8,
      "final_val_data_loss_rise_from_best": 0.0,
      "selected_epoch": 8,
      "epochs_run": 11,
      "early_stopping": true,
      "stopped_epoch": 11,
      "diagnosis": "mitigado por early stopping"
    }
  ]
}